typhooninfo.py
typhooninfo-0.0.3.dist-info/METADATA
typhooninfo-0.0.3.dist-info/WHEEL
typhooninfo-0.0.3.dist-info/entry_points.txt
typhooninfo-0.0.3.dist-info/top_level.txt
typhooninfo-0.0.3.dist-info/RECORD
