Metadata-Version: 2.1
Name: typhooninfo
Version: 0.0.3
Summary: A package for visualization about typhoon in Japan
Home-page: https://github.com/yugo-Ishihara/typhooninfo
Author: yugo ishihara
Author-email: s2022041@stu.musashino-u.ac.jp
License: UNKNOWN
Project-URL: typhooninfo, https://github.com/yugo-Ishihara/typhooninfo
Platform: UNKNOWN
Classifier: Programming Language :: Python :: 3.9
Classifier: License :: OSI Approved :: MIT License
Classifier: Operating System :: OS Independent
Requires-Python: >=3.9
